kat_ran/__init__.py
kat_ran/kat.py
katran/__init__.py
katran/kat.py
katran-0.0.5.dist-info/LICENSE
katran-0.0.5.dist-info/METADATA
katran-0.0.5.dist-info/WHEEL
katran-0.0.5.dist-info/top_level.txt
katran-0.0.5.dist-info/RECORD
