Metadata-Version: 2.1
Name: katran
Version: 0.0.5
Summary: Cat running experience through ya keeboooaard
Home-page: https://github.com/abhijithneilabraham/kat_ran_thru_my_keebord/
Author: Abhijith Neil Abraham
Author-email: abhijithneilabrahampk@gmail.com
License: UNKNOWN
Platform: UNKNOWN
Classifier: Programming Language :: Python :: 3
Classifier: License :: OSI Approved :: MIT License
Classifier: Operating System :: OS Independent
Requires-Python: >=3.4
